01_basic_gates/and_thru_nor/design.sv
`timescale 1ns / 1ps
module and_thru_nor(a,b,c,y);
  input wire a, b, c;
  output wire y;
  
  assign y = ~(~a | ~b | ~c);
endmodule

01_basic_gates/and_thru_nor/testbench.sv
module and_thru_nortb();
  reg p, q, r;
  wire s;
  
  and_thru_nor uut(
    .a(p),
    .b(q),
    .c(r),
    .y(s));
  
  
  initial begin 
    $display("A | B | C");
    p=0; q=0; r=0; #10
    p=0; q=0; r=1; #10
    p=0; q=1; r=0; #10
    p=0; q=1; r=1; #10
    p=1; q=0; r=0; #10
    p=1; q=0; r=1; #10
    p=1; q=1; r=0; #10
    p=1; q=1; r=1; #10
    $finish;
  end
  
  initial begin 
    $monitor("At time %t: a=%b, b=%b, c=%b, y=%b", $time, p,q,r,s);
  end
  
  initial begin
    $dumpfile("and_thru_nor.vcd");
    $dumpvars(0, and_thru_nortb);
  end
  
endmodule

01_basic_gates/and_thru_nor/and_thru_nor.vcd
$date
	Sun Jun  8 01:02:21 2025
$end
$version
	Icarus Verilog
$end
$timescale
	1ps
$end
$scope module and_thru_nortb $end
$var wire 1 ! s $end
$var reg 1 " p $end
$var reg 1 # q $end
$var reg 1 $ r $end
$scope module uut $end
$var wire 1 " a $end
$var wire 1 # b $end
$var wire 1 $ c $end
$var wire 1 ! y $end
$upscope $end
$upscope $end
$enddefinitions $end
$comment Show the parameter values. $end
$dumpall
$end
#0
$dumpvars
0$
0#
0"
0!
$end
#10000
1$
#20000
0$
1#
#30000
1$
#40000
0$
0#
1"
#50000
1$
#60000
0$
1#
#70000
1!
1$
