01_basic_gates/nand_gate/design.sv
module nand_3ip(a,b,c,y);
  input wire a, b, c;
  output wire y;
  
  assign y = ~(a&b&c);
  
endmodule

01_basic_gates/nand_gate/testbench.sv
module nand_3ip_tb();
  reg a, b, c;
  wire y;
  
  nand_3ip uut(
    .a(a),
    .b(b),
    .c(c),
    .y(y)
  );
  
  initial begin
    $display("A | B = Y");
    a=0; b=0; c=0; #10
    a=0; b=0; c=1; #10
    a=0; b=1; c=0; #10
    a=0; b=1; c=1; #10
    a=1; b=0; c=0; #10
    a=1; b=0; c=1; #10
    a=1; b=1; c=0; #10
    a=1; b=1; c=1; #10
    $finish;
  end
  
  initial begin
    $monitor("At time %t : a=%b,b=%b,c=%b,y=%b",$time,a,b,c,y);
  end
  
  initial begin
    $dumpfile("nand_gate.vcd");
    $dumpvars(0, nand_3ip_tb);
  end
  
endmodule

01_basic_gates/nand_gate/nand_gate.vcd
$date
	Sat Jun  7 02:30:51 2025
$end
$version
	Icarus Verilog
$end
$timescale
	1s
$end
$scope module nand_3ip_tb $end
$var wire 1 ! y $end
$var reg 1 " a $end
$var reg 1 # b $end
$var reg 1 $ c $end
$scope module uut $end
$var wire 1 " a $end
$var wire 1 # b $end
$var wire 1 $ c $end
$var wire 1 ! y $end
$upscope $end
$upscope $end
$enddefinitions $end
$comment Show the parameter values. $end
$dumpall
$end
#0
$dumpvars
0$
0#
0"
1!
$end
#10
1$
#20
0$
1#
#30
1$
#40
0$
0#
1"
#50
1$
#60
0$
1#
#70
0!
1$
