01_basic_gates/nor_gate/design.sv
module nor_gate3ip(a,b,c,y);
  input wire a, b, c;
  output wire y;
  
  assign y = ~(a|b|c);
endmodule

01_basic_gates/nand_gate/testbench.sv
module nor_gate3ip_tb();
  reg a, b, c;
  wire y;

  nor_gate3ip uut(
    .a(a),
    .b(b),
    .c(c),
    .y(y)
  );

  initial begin 
    $display("A B C | Y");
    a = 0; b = 0; c = 0; #20;
    a = 0; b = 0; c = 1; #20;
    a = 0; b = 1; c = 0; #20;
    a = 0; b = 1; c = 1; #20;
    a = 1; b = 0; c = 0; #20;
    a = 1; b = 0; c = 1; #20;
    a = 1; b = 1; c = 0; #20;
    a = 1; b = 1; c = 1; #20;
    $finish;
  end

  initial begin
    $monitor("At time %t: a=%b, b=%b, c=%b, y=%b", $time, a, b, c, y);
  end

  initial begin 
    $dumpfile("nor_gate3ip.vcd");
    $dumpvars(0, nor_gate3ip_tb);
  end

endmodule

01_basic_gates/nand_gate/nor_gate3ip.vcd
$date
	Sat Jun  7 00:55:50 2025
$end
$version
	Icarus Verilog
$end
$timescale
	1s
$end
$scope module nor_gate3ip_tb $end
$var wire 1 ! y $end
$var reg 1 " a $end
$var reg 1 # b $end
$var reg 1 $ c $end
$scope module uut $end
$var wire 1 " a $end
$var wire 1 # b $end
$var wire 1 $ c $end
$var wire 1 ! y $end
$upscope $end
$upscope $end
$enddefinitions $end
$comment Show the parameter values. $end
$dumpall
$end
#0
$dumpvars
0$
0#
0"
1!
$end
#20
0!
1$
#40
0$
1#
#60
1$
#80
0$
0#
1"
#100
1$
#120
0$
1#
#140
1$
