01_basic_gates/or_using_nand/design.sv
`timescale 1ns/1ps
module or_using_nand(a,b,c,y);
  input wire a,b,c;
  output wire y;
  
  assign y = ~(~(a&a) & ~(b&b) & ~(c&c));
  
endmodule

01_basic_gates/or_using_nand/testbench.sv
module or_using_nandtb();
  reg p, q, r;
  wire s;
  
  or_using_nand uut(
    .a(p),
    .b(q),
    .c(r),
    .y(s));
  
  initial begin
    p=0; q=0; r=0; #10
    p=0; q=0; r=1; #10
    p=0; q=1; r=0; #10
    p=0; q=1; r=1; #10
    p=1; q=0; r=0; #10
    p=1; q=0; r=1; #10
    p=1; q=1; r=0; #10
    p=1; q=1; r=1; #10
    $finish;
  end
  
  initial begin
    $monitor ("At time %t : a=%b,b=%b,c=%b,y=%b",$time,p,q,r,s);
  end
  
  initial begin
    $dumpfile("or_using_nand.vcd");
    $dumpvars(0, or_using_nandtb);
  end
  
endmodule

01_basic_gates/or_using_nand/or_using_nand.vcd
$date
	Sun Jun  8 01:57:58 2025
$end
$version
	Icarus Verilog
$end
$timescale
	1ps
$end
$scope module or_using_nandtb $end
$var wire 1 ! s $end
$var reg 1 " p $end
$var reg 1 # q $end
$var reg 1 $ r $end
$scope module uut $end
$var wire 1 " a $end
$var wire 1 # b $end
$var wire 1 $ c $end
$var wire 1 ! y $end
$upscope $end
$upscope $end
$enddefinitions $end
$comment Show the parameter values. $end
$dumpall
$end
#0
$dumpvars
0$
0#
0"
0!
$end
#10000
1!
1$
#20000
0$
1#
#30000
1$
#40000
0$
0#
1"
#50000
1$
#60000
0$
1#
#70000
1$
